{"id":1011760,"writings":[],"readings":[{"text":"ぼうっと"},{"text":"ぼおっと","searchOnly":true},{"text":"ぼーっと","priority":{"spec":1}},{"text":"ボウっと","searchOnly":true},{"text":"ボウッと","searchOnly":true},{"text":"ボオッと","searchOnly":true},{"text":"ボーっと","priority":{"spec":1}},{"text":"ボーッと"}],"furigana":[],"meanings":[{"pos":["adv","vs"],"misc":["on-mim"],"glossary":["absent-mindedly","abstractedly","blankly","idly","in a daze","vacantly"]},{"pos":["adv","vs"],"misc":["on-mim"],"glossary":["dimly","faintly","hazily","indistinctly","vaguely"]},{"pos":["adv"],"misc":["on-mim"],"glossary":["flaring up","with a roar (of flames)","with a whoosh"]}]}