{"id":1199120,"writings":[{"text":"解体","priority":{"freq":4,"ichi":1,"news":1}}],"readings":[{"text":"かいたい","priority":{"freq":4,"ichi":1,"news":1}}],"furigana":[{"writing":"解体","reading":"かいたい","furigana":[{"ruby":"解","rt":"かい"},{"ruby":"体","rt":"たい"}]}],"meanings":[{"pos":["n","vs","vt","vi"],"glossary":["demolition","disassembly","dismantling","taking apart","taking down"]},{"pos":["n","vs","vt","vi"],"glossary":["breaking up","dissolution (of an organization, company, etc.)"]},{"pos":["n","vs","vt"],"glossary":["dismemberment","dissection (of a body)"]}]}