{"id":1207530,"writings":[{"text":"額縁","priority":{"freq":31,"news":2,"spec":2}},{"text":"額ぶち","searchOnly":true}],"readings":[{"text":"がくぶち","priority":{"freq":31,"news":2,"spec":2}}],"furigana":[{"writing":"額ぶち","reading":"がくぶち","furigana":[{"ruby":"額","rt":"がく"},{"ruby":"ぶち"}]},{"writing":"額縁","reading":"がくぶち","furigana":[{"ruby":"額","rt":"がく"},{"ruby":"縁","rt":"ぶち"}]}],"meanings":[{"pos":["n"],"glossary":["(picture) frame"]},{"pos":["n"],"glossary":["architrave (of a door, window, etc.)"]}]}