{"id":1238350,"writings":[{"text":"興ざめ"},{"text":"興冷め","irregular":true},{"text":"興覚め","irregular":true},{"text":"興醒め"}],"readings":[{"text":"きょうざめ"}],"furigana":[{"writing":"興ざめ","reading":"きょうざめ","furigana":[{"ruby":"興","rt":"きょう"},{"ruby":"ざめ"}]},{"writing":"興冷め","reading":"きょうざめ","furigana":[{"ruby":"興","rt":"きょう"},{"ruby":"冷","rt":"ざ"},{"ruby":"め"}]},{"writing":"興覚め","reading":"きょうざめ","furigana":[{"ruby":"興","rt":"きょう"},{"ruby":"覚","rt":"ざ"},{"ruby":"め"}]},{"writing":"興醒め","reading":"きょうざめ","furigana":[{"ruby":"興","rt":"きょう"},{"ruby":"醒","rt":"ざ"},{"ruby":"め"}]}],"meanings":[{"pos":["n","adj-na","vs","vi"],"glossary":["damper (e.g. on the party)","loss of interest","spoiled fun","turn-off","wet blanket"]}]}