{"id":1314490,"writings":[{"text":"こと無く"},{"text":"事なく"},{"text":"事無く"}],"readings":[{"text":"ことなく"}],"furigana":[{"writing":"こと無く","reading":"ことなく","furigana":[{"ruby":"こと"},{"ruby":"無","rt":"な"},{"ruby":"く"}]},{"writing":"事なく","reading":"ことなく","furigana":[{"ruby":"事","rt":"こと"},{"ruby":"なく"}]},{"writing":"事無く","reading":"ことなく","furigana":[{"ruby":"事","rt":"こと"},{"ruby":"無","rt":"な"},{"ruby":"く"}]}],"meanings":[{"pos":["adv"],"kanaPreferred":true,"glossary":["uneventfully","without accident"]},{"info":"after verb","pos":["suf"],"kanaPreferred":true,"glossary":["without ..."]}]}