{"id":1349300,"writings":[{"text":"尚","priority":{"freq":5,"ichi":1,"news":1}},{"text":"尚お","irregular":true},{"text":"猶"},{"text":"猶お","irregular":true}],"readings":[{"text":"なお","priority":{"freq":5,"ichi":1,"news":1}}],"furigana":[{"writing":"尚","reading":"なお","furigana":[{"ruby":"尚","rt":"なお"}]},{"writing":"尚お","reading":"なお","furigana":[{"ruby":"尚","rt":"な"},{"ruby":"お"}]},{"writing":"猶","reading":"なお","furigana":[{"ruby":"猶","rt":"なお"}]},{"writing":"猶お","reading":"なお","furigana":[{"ruby":"猶","rt":"な"},{"ruby":"お"}]}],"meanings":[{"pos":["adv"],"kanaPreferred":true,"glossary":["still","yet"]},{"pos":["adv"],"kanaPreferred":true,"glossary":["further","greater","more","still more"]},{"info":"as なお〜ごとし","pos":["adv"],"kanaPreferred":true,"glossary":["as ...","like ..."]},{"pos":["conj"],"kanaPreferred":true,"glossary":["furthermore","in addition","moreover","note that ..."]}]}