{"id":1585315,"writings":[{"text":"六つ","priority":{"ichi":1}},{"text":"６つ"}],"readings":[{"text":"むっつ","priority":{"ichi":1}},{"text":"むつ"}],"furigana":[{"writing":"六つ","reading":"むっつ","furigana":[{"ruby":"六","rt":"むっ"},{"ruby":"つ"}]},{"writing":"六つ","reading":"むつ","furigana":[{"ruby":"六","rt":"む"},{"ruby":"つ"}]},{"writing":"６つ","reading":"むっつ","furigana":[{"ruby":"６","rt":"むっ"},{"ruby":"つ"}]},{"writing":"６つ","reading":"むつ","furigana":[{"ruby":"６","rt":"む"},{"ruby":"つ"}]}],"meanings":[{"pos":["num"],"glossary":["six"]},{"pos":["n"],"glossary":["six years of age"]},{"pos":["n"],"glossary":["six o'clock (old time system)"]}]}