{"id":1591240,"writings":[{"text":"еӮ·д»ҳгҒҸ","priority":{"freq":39,"ichi":2,"news":2}},{"text":"еӮ·гҒӨгҒҸ","priority":{"spec":1}},{"text":"з–өгҒӨгҒҸ","searchOnly":true},{"text":"з–өд»ҳгҒҸ","rare":true}],"readings":[{"text":"гҒҚгҒҡгҒӨгҒҸ","priority":{"freq":39,"ichi":2,"news":2,"spec":1}}],"furigana":[{"writing":"еӮ·гҒӨгҒҸ","reading":"гҒҚгҒҡгҒӨгҒҸ","furigana":[{"ruby":"еӮ·","rt":"гҒҚгҒҡ"},{"ruby":"гҒӨгҒҸ"}]},{"writing":"еӮ·д»ҳгҒҸ","reading":"гҒҚгҒҡгҒӨгҒҸ","furigana":[{"ruby":"еӮ·","rt":"гҒҚгҒҡ"},{"ruby":"д»ҳ","rt":"гҒӨ"},{"ruby":"гҒҸ"}]},{"writing":"з–өгҒӨгҒҸ","reading":"гҒҚгҒҡгҒӨгҒҸ","furigana":[{"ruby":"з–ө","rt":"гҒҚгҒҡ"},{"ruby":"гҒӨгҒҸ"}]},{"writing":"з–өд»ҳгҒҸ","reading":"гҒҚгҒҡгҒӨгҒҸ","furigana":[{"ruby":"з–ө","rt":"гҒҚгҒҡ"},{"ruby":"д»ҳ","rt":"гҒӨ"},{"ruby":"гҒҸ"}]}],"meanings":[{"pos":["v5k","vi"],"glossary":["to be wounded","to get injured"]},{"pos":["v5k","vi"],"glossary":["to get hurt feelings"]},{"pos":["v5k","vi"],"glossary":["to get chipped","to get damaged","to get scratched"]}]}