{"id":1597040,"writings":[{"text":"立つ","priority":{"freq":21,"ichi":1,"news":1}}],"readings":[{"text":"たつ","priority":{"freq":21,"ichi":1,"news":1}}],"furigana":[{"writing":"立つ","reading":"たつ","furigana":[{"ruby":"立","rt":"た"},{"ruby":"つ"}]}],"meanings":[{"pos":["v5t","vi"],"glossary":["to get to one's feet","to rise","to stand (up)","to stand on end (e.g. of hairs)","to stick up"]},{"pos":["v5t","vi"],"glossary":["to be situated (in, on)","to stand (in a position; of a person, tree, building, etc.)"]},{"pos":["v5t","vi"],"glossary":["to be (in difficulties, the lead, etc.)","to position oneself","to put oneself (in a position or situation)","to take up (a position, post, etc.)"]},{"pos":["v5t","vi"],"glossary":["to leave (to do something)"]},{"info":"oft. written as 発つ","pos":["v5t","vi"],"glossary":["to depart (on a journey, trip, etc.)","to leave","to set off","to start"]},{"pos":["v5t","vi"],"glossary":["to get stuck (into; of an arrow, thorn etc.)","to pierce"]},{"pos":["v5t","vi"],"glossary":["to appear (of a rainbow, clouds, etc.)","to begin to blow (of a wind, breeze, etc.)","to develop (of a haze, waves, etc.)","to form (of steam, bubbles, etc.)","to rise (of smoke, waves, etc.)"]},{"pos":["v5t","vi"],"glossary":["to be become widely known","to spread (of a rumour, reputation, etc.)"]},{"pos":["v5t","vi"],"glossary":["to run","to stand (for election)"]},{"info":"also written as 起つ","pos":["v5t","vi"],"glossary":["to act","to rise (up)","to rouse oneself","to take action"]},{"info":"also written as 勃つ","pos":["v5t","vi"],"misc":["col"],"glossary":["to become erect (e.g. of nipples)","to have an erection"]},{"pos":["v5t","vi"],"glossary":["to be established (of a policy, plan, objective, etc.)","to be formed"]},{"pos":["v5t","vi"],"glossary":["to be logical","to be reasonable","to be valid (of an argument, logic, etc.)","to hold up","to hold water","to stand up (e.g. of evidence)"]},{"pos":["v5t","vi"],"glossary":["to be maintained","to be preserved (of one's reputation, honour, etc.)","to be saved","to be sustained (of a living, business, etc.)","to survive"]},{"pos":["v5t","vi"],"glossary":["to begin","to start (of a season)"]},{"pos":["v5t","vi"],"glossary":["to be held (of a market)"]},{"pos":["v5t","vi"],"glossary":["to be closed","to be shut","to shut (of a door, shoji, etc.)"]},{"pos":["v5t","vi"],"glossary":["to be (the result of a division)"]}]}