{"id":1606370,"writings":[{"text":"類型","priority":{"freq":29,"ichi":2,"news":2}},{"text":"類形","searchOnly":true}],"readings":[{"text":"るいけい","priority":{"freq":29,"ichi":2,"news":2}}],"furigana":[{"writing":"類型","reading":"るいけい","furigana":[{"ruby":"類","rt":"るい"},{"ruby":"型","rt":"けい"}]},{"writing":"類形","reading":"るいけい","furigana":[{"ruby":"類","rt":"るい"},{"ruby":"形","rt":"けい"}]}],"meanings":[{"pos":["n"],"glossary":["breed","genre","pattern","shape","type"]},{"pos":["n"],"glossary":["similar pattern","similar type"]}]}