{"id":1633160,"writings":[{"text":"и‚©г‚’гЃ„гЃ‹г‚‰гЃ›г‚‹"},{"text":"и‚©г‚’жЂ’г‚‰гЃ›г‚‹"}],"readings":[{"text":"гЃ‹гЃџг‚’гЃ„гЃ‹г‚‰гЃ›г‚‹"}],"furigana":[{"writing":"и‚©г‚’гЃ„гЃ‹г‚‰гЃ›г‚‹","reading":"гЃ‹гЃџг‚’гЃ„гЃ‹г‚‰гЃ›г‚‹","furigana":[{"ruby":"и‚©","rt":"гЃ‹гЃџ"},{"ruby":"г‚’гЃ„гЃ‹г‚‰гЃ›г‚‹"}]},{"writing":"и‚©г‚’жЂ’г‚‰гЃ›г‚‹","reading":"гЃ‹гЃџг‚’гЃ„гЃ‹г‚‰гЃ›г‚‹","furigana":[{"ruby":"и‚©","rt":"гЃ‹гЃџ"},{"ruby":"г‚’"},{"ruby":"жЂ’","rt":"гЃ„гЃ‹"},{"ruby":"г‚‰гЃ›г‚‹"}]}],"meanings":[{"pos":["exp","v1"],"misc":["id"],"glossary":["to square one's shoulders (in order to intimidate)"]}]}