{"id":1830540,"writings":[{"text":"なまり節"},{"text":"生り節"},{"text":"生節"}],"readings":[{"text":"なまぶし","useWith":["生節"]},{"text":"なまりぶし"}],"furigana":[{"writing":"なまり節","reading":"なまりぶし","furigana":[{"ruby":"なまり"},{"ruby":"節","rt":"ぶし"}]},{"writing":"生り節","reading":"なまりぶし","furigana":[{"ruby":"生","rt":"なま"},{"ruby":"り"},{"ruby":"節","rt":"ぶし"}]},{"writing":"生節","reading":"なまぶし","furigana":[{"ruby":"生節","rt":"なまぶし"}]},{"writing":"生節","reading":"なまりぶし","furigana":[{"ruby":"生節","rt":"なまりぶし"}]}],"meanings":[{"pos":["n"],"glossary":["boiled and half-dried bonito"]}]}