{"id":2011300,"writings":[{"text":"小やみ","searchOnly":true},{"text":"小止み"}],"readings":[{"text":"おやみ"},{"text":"こやみ"}],"furigana":[{"writing":"小やみ","reading":"おやみ","furigana":[{"ruby":"小","rt":"お"},{"ruby":"やみ"}]},{"writing":"小やみ","reading":"こやみ","furigana":[{"ruby":"小","rt":"こ"},{"ruby":"やみ"}]},{"writing":"小止み","reading":"おやみ","furigana":[{"ruby":"小","rt":"お"},{"ruby":"止","rt":"や"},{"ruby":"み"}]},{"writing":"小止み","reading":"こやみ","furigana":[{"ruby":"小","rt":"こ"},{"ruby":"止","rt":"や"},{"ruby":"み"}]}],"meanings":[{"pos":["n"],"glossary":["break","lull (e.g. in the rain)"]}]}