{"id":2102490,"writings":[{"text":"大目玉をくらう"},{"text":"大目玉を食らう"}],"readings":[{"text":"おおめだまをくらう"}],"furigana":[{"writing":"大目玉をくらう","reading":"おおめだまをくらう","furigana":[{"ruby":"大","rt":"おお"},{"ruby":"目","rt":"め"},{"ruby":"玉","rt":"だま"},{"ruby":"をくらう"}]},{"writing":"大目玉を食らう","reading":"おおめだまをくらう","furigana":[{"ruby":"大","rt":"おお"},{"ruby":"目","rt":"め"},{"ruby":"玉","rt":"だま"},{"ruby":"を"},{"ruby":"食","rt":"く"},{"ruby":"らう"}]}],"meanings":[{"pos":["exp","v5u"],"glossary":["to get scolded severely"]}]}