{"id":2224860,"writings":[{"text":"申し込み〆切"},{"text":"申し込み締め切り"},{"text":"申し込み締切り"},{"text":"申込締切"}],"readings":[{"text":"もうしこみしめきり"}],"furigana":[{"writing":"申し込み締め切り","reading":"もうしこみしめきり","furigana":[{"ruby":"申","rt":"もう"},{"ruby":"し"},{"ruby":"込","rt":"こ"},{"ruby":"み"},{"ruby":"締","rt":"し"},{"ruby":"め"},{"ruby":"切","rt":"き"},{"ruby":"り"}]},{"writing":"申し込み締切り","reading":"もうしこみしめきり","furigana":[{"ruby":"申","rt":"もう"},{"ruby":"し"},{"ruby":"込","rt":"こ"},{"ruby":"み"},{"ruby":"締","rt":"しめ"},{"ruby":"切","rt":"き"},{"ruby":"り"}]},{"writing":"申込締切","reading":"もうしこみしめきり","furigana":[{"ruby":"申","rt":"もうし"},{"ruby":"込","rt":"こみ"},{"ruby":"締","rt":"しめ"},{"ruby":"切","rt":"きり"}]}],"meanings":[{"pos":["n"],"glossary":["application deadline"]}]}