{"id":2737880,"writings":[{"text":"ごみ屑"},{"text":"ゴミ屑"},{"text":"塵屑"}],"readings":[{"text":"ごみくず","useWith":["ごみ屑","塵屑"]},{"text":"ゴミくず","useWith":["ゴミ屑"]},{"text":"ゴミクズ","noKanji":true}],"furigana":[{"writing":"ごみ屑","reading":"ごみくず","furigana":[{"ruby":"ごみ"},{"ruby":"屑","rt":"くず"}]},{"writing":"ゴミ屑","reading":"ゴミくず","furigana":[{"ruby":"ゴミ"},{"ruby":"屑","rt":"くず"}]},{"writing":"塵屑","reading":"ごみくず","furigana":[{"ruby":"塵","rt":"ごみ"},{"ruby":"屑","rt":"くず"}]}],"meanings":[{"pos":["n"],"kanaPreferred":true,"glossary":["garbage","junk","trash"]}]}