{"id":2833239,"writings":[{"text":"てんびん秤"},{"text":"天秤ばかり"},{"text":"天秤秤"}],"readings":[{"text":"てんびんばかり"}],"furigana":[{"writing":"てんびん秤","reading":"てんびんばかり","furigana":[{"ruby":"てんびん"},{"ruby":"秤","rt":"ばかり"}]},{"writing":"天秤ばかり","reading":"てんびんばかり","furigana":[{"ruby":"天","rt":"てん"},{"ruby":"秤","rt":"びん"},{"ruby":"ばかり"}]},{"writing":"天秤秤","reading":"てんびんばかり","furigana":[{"ruby":"天","rt":"てん"},{"ruby":"秤","rt":"びん"},{"ruby":"秤","rt":"ばかり"}]}],"meanings":[{"pos":["n"],"glossary":["balance","balance scale"]}]}