{"id":2836255,"writings":[{"text":"呉"}],"readings":[{"text":"ご"}],"furigana":[{"writing":"呉","reading":"ご","furigana":[{"ruby":"呉","rt":"ご"}]}],"meanings":[{"pos":["n"],"glossary":["Wu (region in China, south of the lower Yangtze)"]},{"pos":["n"],"misc":["hist"],"glossary":["Southern Wu","Wu (kingdom in China during the Five Dynasties and Ten Kingdoms era; 902-937 CE)"]},{"pos":["n"],"misc":["hist"],"glossary":["Eastern Wu","Sun Wu","Wu (kingdom in China during the Three Kingdoms era; 222-280 CE)"]},{"pos":["n"],"misc":["hist"],"glossary":["Wu (kingdom in China during the Spring and Autumn era; 11th century-473 BCE)"]}]}