{"id":2866685,"writings":[{"text":"卯の花くたし"},{"text":"卯の花くだし","searchOnly":true},{"text":"卯の花腐し"}],"readings":[{"text":"うのはなくたし"},{"text":"うのはなくだし","searchOnly":true}],"furigana":[{"writing":"卯の花くたし","reading":"うのはなくたし","furigana":[{"ruby":"卯","rt":"う"},{"ruby":"の"},{"ruby":"花","rt":"はな"},{"ruby":"くたし"}]},{"writing":"卯の花くだし","reading":"うのはなくだし","furigana":[{"ruby":"卯","rt":"う"},{"ruby":"の"},{"ruby":"花","rt":"はな"},{"ruby":"くだし"}]}],"meanings":[{"pos":["exp","n"],"misc":["poet"],"glossary":["long rains (in early summer)"]}]}