{"id":101781,"sentence":"彼は東京で１０年間商売をしていた。","meaning":"He carried on business for ten years in Tokyo.","words":[{"word":1483070,"furigana":[{"ruby":"彼","rt":"かれ"}]},{"word":null,"furigana":[{"ruby":"は"}]},{"word":1447690,"furigana":[{"ruby":"東","rt":"とう"},{"ruby":"京","rt":"きょう"}]},{"word":null,"furigana":[{"ruby":"で１０"}]},{"word":1468380,"furigana":[{"ruby":"年","rt":"ねん"},{"ruby":"間","rt":"かん"}]},{"word":1347200,"furigana":[{"ruby":"商","rt":"しょう"},{"ruby":"売","rt":"ばい"}]},{"word":null,"furigana":[{"ruby":"を"}]},{"word":1157170,"furigana":[{"ruby":"していた"}]},{"word":null,"furigana":[{"ruby":"。"}]}]}