{"id":103097,"sentence":"彼は切手を５００枚も集めた。","meaning":"He has collected no fewer than five hundred stamps.","words":[{"word":1483070,"furigana":[{"ruby":"彼","rt":"かれ"}]},{"word":null,"furigana":[{"ruby":"は"}]},{"word":1385070,"furigana":[{"ruby":"切","rt":"きっ"},{"ruby":"手","rt":"て"}]},{"word":null,"furigana":[{"ruby":"を５００"}]},{"word":1524610,"furigana":[{"ruby":"枚","rt":"まい"}]},{"word":null,"furigana":[{"ruby":"も"}]},{"word":1333560,"furigana":[{"ruby":"集","rt":"あつ"},{"ruby":"めた"}]},{"word":null,"furigana":[{"ruby":"。"}]}]}