{"id":106480,"sentence":"彼は支配人に会わなければならないと言った。","meaning":"He said that he must see the manager.","words":[{"word":1483070,"furigana":[{"ruby":"彼","rt":"かれ"}]},{"word":null,"furigana":[{"ruby":"は"}]},{"word":1646570,"furigana":[{"ruby":"支","rt":"し"},{"ruby":"配","rt":"はい"},{"ruby":"人","rt":"にん"}]},{"word":null,"furigana":[{"ruby":"に"}]},{"word":1198180,"furigana":[{"ruby":"会","rt":"あ"},{"ruby":"わ"}]},{"word":1632350,"furigana":[{"ruby":"なければならない"}]},{"word":null,"furigana":[{"ruby":"と"}]},{"word":1587040,"furigana":[{"ruby":"言","rt":"い"},{"ruby":"った"}]},{"word":null,"furigana":[{"ruby":"。"}]}]}