{"id":107596,"sentence":"彼は言い訳として二、三述べた。","meaning":"He said a few words by way of apology.","words":[{"word":1483070,"furigana":[{"ruby":"彼","rt":"かれ"}]},{"word":null,"furigana":[{"ruby":"は"}]},{"word":1587030,"furigana":[{"ruby":"言","rt":"い"},{"ruby":"い"},{"ruby":"訳","rt":"わけ"}]},{"word":null,"furigana":[{"ruby":"として"}]},{"word":1461140,"furigana":[{"ruby":"二","rt":"に"}]},{"word":null,"furigana":[{"ruby":"、"}]},{"word":1579350,"furigana":[{"ruby":"三","rt":"さん"}]},{"word":1340820,"furigana":[{"ruby":"述","rt":"の"},{"ruby":"べた"}]},{"word":null,"furigana":[{"ruby":"。"}]}]}