{"id":107574,"sentence":"彼は言葉とか手招きで話そうとした。","meaning":"He tried to speak by word or gesture.","words":[{"word":1483070,"furigana":[{"ruby":"彼","rt":"かれ"}]},{"word":null,"furigana":[{"ruby":"は"}]},{"word":1264540,"furigana":[{"ruby":"言葉"}]},{"word":null,"furigana":[{"ruby":"とか"}]},{"word":1327850,"furigana":[{"ruby":"手","rt":"て"},{"ruby":"招","rt":"まね"},{"ruby":"き"}]},{"word":null,"furigana":[{"ruby":"で"}]},{"word":1562350,"furigana":[{"ruby":"話","rt":"はな"},{"ruby":"そう"}]},{"word":1854680,"furigana":[{"ruby":"とした"}]},{"word":null,"furigana":[{"ruby":"。"}]}]}