{"id":115547,"sentence":"彼は、現れるといつも大騒ぎをする。","meaning":"He never turns up without making a fuss.","words":[{"word":1483070,"furigana":[{"ruby":"彼","rt":"かれ"}]},{"word":null,"furigana":[{"ruby":"は、"}]},{"word":1263510,"furigana":[{"ruby":"現","rt":"あらわ"},{"ruby":"れる"}]},{"word":null,"furigana":[{"ruby":"と"}]},{"word":1188890,"furigana":[{"ruby":"いつも"}]},{"word":1414410,"furigana":[{"ruby":"大","rt":"おお"},{"ruby":"騒","rt":"さわ"},{"ruby":"ぎ"}]},{"word":null,"furigana":[{"ruby":"を"}]},{"word":1157170,"furigana":[{"ruby":"する"}]},{"word":null,"furigana":[{"ruby":"。"}]}]}