{"id":117905,"sentence":"彼の解決策は一時的なものだった。","meaning":"His solution was only a temporary one.","words":[{"word":1483070,"furigana":[{"ruby":"彼","rt":"かれ"},{"ruby":"の"}]},{"word":1198970,"furigana":[{"ruby":"解","rt":"かい"},{"ruby":"決","rt":"けつ"},{"ruby":"策","rt":"さく"}]},{"word":null,"furigana":[{"ruby":"は"}]},{"word":1162980,"furigana":[{"ruby":"一","rt":"いち"},{"ruby":"時","rt":"じ"},{"ruby":"的","rt":"てき"},{"ruby":"な"}]},{"word":1502390,"furigana":[{"ruby":"もの"}]},{"word":1564200,"furigana":[{"ruby":"だった"}]},{"word":null,"furigana":[{"ruby":"。"}]}]}