{"id":122526,"sentence":"日本はアメリカの農産物の最大の輸入国である。","meaning":"Japan is the largest importer of U.S. farm products.","words":[{"word":1582710,"furigana":[{"ruby":"日本","rt":"にっぽん"}]},{"word":null,"furigana":[{"ruby":"は"}]},{"word":1149830,"furigana":[{"ruby":"アメリカ"}]},{"word":null,"furigana":[{"ruby":"の"}]},{"word":1470710,"furigana":[{"ruby":"農","rt":"のう"},{"ruby":"産","rt":"さん"},{"ruby":"物","rt":"ぶつ"}]},{"word":null,"furigana":[{"ruby":"の"}]},{"word":1294180,"furigana":[{"ruby":"最","rt":"さい"},{"ruby":"大","rt":"だい"}]},{"word":null,"furigana":[{"ruby":"の"}]},{"word":1538870,"furigana":[{"ruby":"輸","rt":"しゅ"},{"ruby":"入","rt":"にゅう"}]},{"word":1592250,"furigana":[{"ruby":"国","rt":"くに"}]},{"word":null,"furigana":[{"ruby":"である。"}]}]}