{"id":124103,"sentence":"当局は自国の通貨を何とか安定させた。","meaning":"The authorities managed to stabilize the currency.","words":[{"word":1449030,"furigana":[{"ruby":"当","rt":"とう"},{"ruby":"局","rt":"きょく"}]},{"word":null,"furigana":[{"ruby":"は"}]},{"word":1317710,"furigana":[{"ruby":"自","rt":"じ"},{"ruby":"国","rt":"こく"}]},{"word":null,"furigana":[{"ruby":"の"}]},{"word":1433050,"furigana":[{"ruby":"通","rt":"つう"},{"ruby":"貨","rt":"か"}]},{"word":null,"furigana":[{"ruby":"を"}]},{"word":1188420,"furigana":[{"ruby":"何","rt":"なん"},{"ruby":"とか"}]},{"word":1154120,"furigana":[{"ruby":"安","rt":"あん"},{"ruby":"定","rt":"てい"}]},{"word":null,"furigana":[{"ruby":"させた"}]},{"word":null,"furigana":[{"ruby":"。"}]}]}