{"id":124960,"sentence":"転んでひざを擦り剥かないようにしなさい。","meaning":"Take care not to fall down and skin your knee.","words":[{"word":1582130,"furigana":[{"ruby":"転","rt":"ころ"},{"ruby":"んで"}]},{"word":1487320,"furigana":[{"ruby":"ひざ"}]},{"word":null,"furigana":[{"ruby":"を"}]},{"word":1298860,"furigana":[{"ruby":"擦","rt":"す"},{"ruby":"り"},{"ruby":"剥","rt":"む"},{"ruby":"かない"}]},{"word":1013120,"furigana":[{"ruby":"ようにし"}]},{"word":2192950,"furigana":[{"ruby":"なさい"}]},{"word":null,"furigana":[{"ruby":"。"}]}]}