{"id":126132,"sentence":"町のこの地域は私には不案内です。","meaning":"This part of the city is strange to me.","words":[{"word":1603990,"furigana":[{"ruby":"町","rt":"まち"}]},{"word":null,"furigana":[{"ruby":"の"}]},{"word":1582920,"furigana":[{"ruby":"この"}]},{"word":1420800,"furigana":[{"ruby":"地","rt":"ち"},{"ruby":"域","rt":"いき"}]},{"word":null,"furigana":[{"ruby":"は"}]},{"word":1311110,"furigana":[{"ruby":"私","rt":"わたし"}]},{"word":null,"furigana":[{"ruby":"には"}]},{"word":1491200,"furigana":[{"ruby":"不","rt":"ふ"},{"ruby":"案","rt":"あん"},{"ruby":"内","rt":"ない"}]},{"word":null,"furigana":[{"ruby":"です。"}]}]}