{"id":126120,"sentence":"町の灯りはとても明るくとてもちかくなっていて通りの灯かりは夜中輝いています。","meaning":"Now the lights of the city were bright and very close, and the streetlights shone all night.","words":[{"word":1603990,"furigana":[{"ruby":"町","rt":"まち"}]},{"word":null,"furigana":[{"ruby":"の"}]},{"word":1586210,"furigana":[{"ruby":"灯り"}]},{"word":null,"furigana":[{"ruby":"は"}]},{"word":1008630,"furigana":[{"ruby":"とても"}]},{"word":1532350,"furigana":[{"ruby":"明","rt":"あか"},{"ruby":"るく"}]},{"word":1008630,"furigana":[{"ruby":"とても"}]},{"word":1242130,"furigana":[{"ruby":"ちかく"}]},{"word":1375610,"furigana":[{"ruby":"なっていて"}]},{"word":1432920,"furigana":[{"ruby":"通","rt":"とお"},{"ruby":"り"}]},{"word":null,"furigana":[{"ruby":"の"}]},{"word":1586210,"furigana":[{"ruby":"灯かり"}]},{"word":null,"furigana":[{"ruby":"は"}]},{"word":1584830,"furigana":[{"ruby":"夜","rt":"や"},{"ruby":"中","rt":"ちゅう"}]},{"word":1224020,"furigana":[{"ruby":"輝","rt":"かがや"},{"ruby":"いています"}]},{"word":null,"furigana":[{"ruby":"。"}]}]}