{"id":136804,"sentence":"誰でも自分の意見を持つ権利がある。","meaning":"Everyone is entitled to his own opinion.","words":[{"word":1416850,"furigana":[{"ruby":"誰","rt":"だれ"},{"ruby":"でも"}]},{"word":1318610,"furigana":[{"ruby":"自","rt":"じ"},{"ruby":"分","rt":"ぶん"}]},{"word":null,"furigana":[{"ruby":"の"}]},{"word":1156530,"furigana":[{"ruby":"意","rt":"い"},{"ruby":"見","rt":"けん"}]},{"word":null,"furigana":[{"ruby":"を"}]},{"word":1315720,"furigana":[{"ruby":"持","rt":"も"},{"ruby":"つ"}]},{"word":1258200,"furigana":[{"ruby":"権","rt":"けん"},{"ruby":"利","rt":"り"}]},{"word":null,"furigana":[{"ruby":"が"}]},{"word":1296400,"furigana":[{"ruby":"ある"}]},{"word":null,"furigana":[{"ruby":"。"}]}]}