{"id":138802,"sentence":"他にその仕事をこなせる人はいないよ。","meaning":"No one else can fill that job.","words":[{"word":1203260,"furigana":[{"ruby":"他","rt":"ほか"}]},{"word":null,"furigana":[{"ruby":"に"}]},{"word":1006830,"furigana":[{"ruby":"その"}]},{"word":1304970,"furigana":[{"ruby":"仕","rt":"し"},{"ruby":"事","rt":"ごと"}]},{"word":null,"furigana":[{"ruby":"を"}]},{"word":1612850,"furigana":[{"ruby":"こなせる"}]},{"word":1580640,"furigana":[{"ruby":"人","rt":"ひと"}]},{"word":null,"furigana":[{"ruby":"は"}]},{"word":1577980,"furigana":[{"ruby":"いない"}]},{"word":null,"furigana":[{"ruby":"よ。"}]}]}