{"id":149567,"sentence":"失礼ですが、電話番号をお間違いではないでしょうか。","meaning":"Sorry, but I think you've got the wrong number.","words":[{"word":1320230,"furigana":[{"ruby":"失礼"}]},{"word":null,"furigana":[{"ruby":"ですが、"}]},{"word":1443840,"furigana":[{"ruby":"電","rt":"でん"},{"ruby":"話","rt":"わ"}]},{"word":1482290,"furigana":[{"ruby":"番","rt":"ばん"},{"ruby":"号","rt":"ごう"}]},{"word":null,"furigana":[{"ruby":"を"}]},{"word":2826528,"furigana":[{"ruby":"お"}]},{"word":1215320,"furigana":[{"ruby":"間","rt":"ま"},{"ruby":"違","rt":"ちが"},{"ruby":"い"}]},{"word":2823770,"furigana":[{"ruby":"ではない"}]},{"word":null,"furigana":[{"ruby":"でしょうか。"}]}]}