{"id":151941,"sentence":"私達の先生は来月アメリカに行きます。","meaning":"Our teacher is going to the USA next month.","words":[{"word":1311300,"furigana":[{"ruby":"私","rt":"わたくし"},{"ruby":"達"}]},{"word":null,"furigana":[{"ruby":"の"}]},{"word":1387990,"furigana":[{"ruby":"先","rt":"せん"},{"ruby":"生","rt":"せい"}]},{"word":null,"furigana":[{"ruby":"は"}]},{"word":1547900,"furigana":[{"ruby":"来","rt":"らい"},{"ruby":"月","rt":"げつ"}]},{"word":1149830,"furigana":[{"ruby":"アメリカ"}]},{"word":null,"furigana":[{"ruby":"に"}]},{"word":1578850,"furigana":[{"ruby":"行","rt":"い"},{"ruby":"きます"}]},{"word":null,"furigana":[{"ruby":"。"}]}]}