{"id":153226,"sentence":"私は彼女の話し方は好きではない。","meaning":"I don't like the way she speaks.","words":[{"word":1311110,"furigana":[{"ruby":"私","rt":"わたし"}]},{"word":null,"furigana":[{"ruby":"は"}]},{"word":1483150,"furigana":[{"ruby":"彼","rt":"かの"},{"ruby":"女","rt":"じょ"},{"ruby":"の"}]},{"word":1562340,"furigana":[{"ruby":"話","rt":"はな"},{"ruby":"し"},{"ruby":"方","rt":"かた"}]},{"word":null,"furigana":[{"ruby":"は"}]},{"word":1277450,"furigana":[{"ruby":"好","rt":"す"},{"ruby":"き"}]},{"word":2823770,"furigana":[{"ruby":"ではない"}]},{"word":null,"furigana":[{"ruby":"。"}]}]}