{"id":161837,"sentence":"私はあなたから責任を問われることは何も無い。","meaning":"I am not answerable to you for anything.","words":[{"word":1311110,"furigana":[{"ruby":"私","rt":"わたし"}]},{"word":null,"furigana":[{"ruby":"は"}]},{"word":1223615,"furigana":[{"ruby":"あなた"}]},{"word":null,"furigana":[{"ruby":"から"}]},{"word":2191940,"furigana":[{"ruby":"責","rt":"せき"},{"ruby":"任","rt":"にん"},{"ruby":"を"},{"ruby":"問","rt":"と"},{"ruby":"われる"}]},{"word":1313580,"furigana":[{"ruby":"こと"}]},{"word":null,"furigana":[{"ruby":"は"}]},{"word":1188490,"furigana":[{"ruby":"何","rt":"なに"},{"ruby":"も"}]},{"word":1529520,"furigana":[{"ruby":"無","rt":"な"},{"ruby":"い"}]},{"word":null,"furigana":[{"ruby":"。"}]}]}