{"id":166334,"sentence":"私たちはそれらの単語を全て暗記できるとは限らない。","meaning":"We won't be able to learn all of the words by heart.","words":[{"word":1311300,"furigana":[{"ruby":"私","rt":"わたくし"},{"ruby":"たち"}]},{"word":null,"furigana":[{"ruby":"は"}]},{"word":1007070,"furigana":[{"ruby":"それら"}]},{"word":null,"furigana":[{"ruby":"の"}]},{"word":1417330,"furigana":[{"ruby":"単","rt":"たん"},{"ruby":"語","rt":"ご"}]},{"word":null,"furigana":[{"ruby":"を"}]},{"word":1595730,"furigana":[{"ruby":"全","rt":"すべ"},{"ruby":"て"}]},{"word":1586910,"furigana":[{"ruby":"暗","rt":"あん"},{"ruby":"記","rt":"き"}]},{"word":1340450,"furigana":[{"ruby":"できる"}]},{"word":2070730,"furigana":[{"ruby":"とは"},{"ruby":"限","rt":"かぎ"},{"ruby":"らない"}]},{"word":null,"furigana":[{"ruby":"。"}]}]}