{"id":170217,"sentence":"財政危機に直面している発展途上国もある。","meaning":"Some developing countries are faced with financial crises.","words":[{"word":1296860,"furigana":[{"ruby":"財","rt":"ざい"},{"ruby":"政","rt":"せい"},{"ruby":"危","rt":"き"},{"ruby":"機","rt":"き"}]},{"word":null,"furigana":[{"ruby":"に"}]},{"word":1431540,"furigana":[{"ruby":"直","rt":"ちょく"},{"ruby":"面","rt":"めん"}]},{"word":1157170,"furigana":[{"ruby":"している"}]},{"word":1477740,"furigana":[{"ruby":"発","rt":"はっ"},{"ruby":"展","rt":"てん"},{"ruby":"途","rt":"と"},{"ruby":"上","rt":"じょう"},{"ruby":"国","rt":"こく"}]},{"word":null,"furigana":[{"ruby":"も"}]},{"word":1296400,"furigana":[{"ruby":"ある"}]},{"word":null,"furigana":[{"ruby":"。"}]}]}