{"id":172079,"sentence":"今度日本に返って来られるのはずっと先のことでしょう。","meaning":"I guess it will be a long time before I can return to Japan.","words":[{"word":1289370,"furigana":[{"ruby":"今","rt":"こん"},{"ruby":"度","rt":"ど"}]},{"word":1582710,"furigana":[{"ruby":"日本","rt":"にっぽん"}]},{"word":null,"furigana":[{"ruby":"に"}]},{"word":1512150,"furigana":[{"ruby":"返","rt":"かえ"},{"ruby":"って"}]},{"word":1547720,"furigana":[{"ruby":"来","rt":"く"},{"ruby":"られる"}]},{"word":null,"furigana":[{"ruby":"のはずっと"}]},{"word":1387210,"furigana":[{"ruby":"先","rt":"さき"}]},{"word":1469800,"furigana":[{"ruby":"の"}]},{"word":1313580,"furigana":[{"ruby":"こと"}]},{"word":null,"furigana":[{"ruby":"でしょう。"}]}]}