{"id":173499,"sentence":"紅茶にレモンの風味を加えて下さい。","meaning":"Please add lemon flavor to the tea.","words":[{"word":1280770,"furigana":[{"ruby":"紅","rt":"こう"},{"ruby":"茶","rt":"ちゃ"}]},{"word":null,"furigana":[{"ruby":"に"}]},{"word":1146020,"furigana":[{"ruby":"レモン"}]},{"word":null,"furigana":[{"ruby":"の"}]},{"word":1624810,"furigana":[{"ruby":"風","rt":"ふう"},{"ruby":"味","rt":"み"}]},{"word":null,"furigana":[{"ruby":"を"}]},{"word":1189960,"furigana":[{"ruby":"加","rt":"くわ"},{"ruby":"えて"}]},{"word":1184270,"furigana":[{"ruby":"下","rt":"くだ"},{"ruby":"さい"}]},{"word":null,"furigana":[{"ruby":"。"}]}]}