{"id":177082,"sentence":"君は相撲取りの隣にくるとちっぽけにみえる。","meaning":"You look tiny next to a sumo wrestler.","words":[{"word":1247250,"furigana":[{"ruby":"君","rt":"きみ"}]},{"word":null,"furigana":[{"ruby":"は"}]},{"word":1401380,"furigana":[{"ruby":"相撲取り"}]},{"word":null,"furigana":[{"ruby":"の"}]},{"word":1555830,"furigana":[{"ruby":"隣","rt":"となり"}]},{"word":null,"furigana":[{"ruby":"に"}]},{"word":1547720,"furigana":[{"ruby":"くる"}]},{"word":null,"furigana":[{"ruby":"とちっぽけに"}]},{"word":1259140,"furigana":[{"ruby":"みえる"}]},{"word":null,"furigana":[{"ruby":"。"}]}]}