{"id":177337,"sentence":"君は君自身で判断しなければいけない。","meaning":"You must judge for yourself.","words":[{"word":1247250,"furigana":[{"ruby":"君","rt":"きみ"}]},{"word":null,"furigana":[{"ruby":"は"}]},{"word":1247250,"furigana":[{"ruby":"君","rt":"きみ"}]},{"word":1318000,"furigana":[{"ruby":"自","rt":"じ"},{"ruby":"身","rt":"しん"}]},{"word":null,"furigana":[{"ruby":"で"}]},{"word":1478620,"furigana":[{"ruby":"判","rt":"はん"},{"ruby":"断","rt":"だん"}]},{"word":1157170,"furigana":[{"ruby":"し"}]},{"word":1632350,"furigana":[{"ruby":"なければいけない"}]},{"word":null,"furigana":[{"ruby":"。"}]}]}