{"id":190107,"sentence":"一番近い館内電話はどこにあるか教えて下さい。","meaning":"Can you tell me where the nearest courtesy phone is?","words":[{"word":1165970,"furigana":[{"ruby":"一","rt":"いち"},{"ruby":"番","rt":"ばん"}]},{"word":1242130,"furigana":[{"ruby":"近","rt":"ちか"},{"ruby":"い"}]},{"word":1614320,"furigana":[{"ruby":"館","rt":"かん"},{"ruby":"内","rt":"ない"}]},{"word":1443840,"furigana":[{"ruby":"電","rt":"でん"},{"ruby":"話","rt":"わ"}]},{"word":null,"furigana":[{"ruby":"は"}]},{"word":1577140,"furigana":[{"ruby":"どこ"}]},{"word":null,"furigana":[{"ruby":"に"}]},{"word":1296400,"furigana":[{"ruby":"ある"}]},{"word":null,"furigana":[{"ruby":"か"}]},{"word":1236900,"furigana":[{"ruby":"教","rt":"おし"},{"ruby":"えて"}]},{"word":1184270,"furigana":[{"ruby":"下","rt":"くだ"},{"ruby":"さい"}]},{"word":null,"furigana":[{"ruby":"。"}]}]}