{"id":191899,"sentence":"わたしの叔父はその通りに自分の店を持っている。","meaning":"My uncle has a store along the street.","words":[{"word":1311110,"furigana":[{"ruby":"わたしの"}]},{"word":1607070,"furigana":[{"ruby":"叔父","rt":"おじ"}]},{"word":null,"furigana":[{"ruby":"は"}]},{"word":2057830,"furigana":[{"ruby":"その"},{"ruby":"通","rt":"とお"},{"ruby":"り"}]},{"word":null,"furigana":[{"ruby":"に"}]},{"word":1318610,"furigana":[{"ruby":"自","rt":"じ"},{"ruby":"分","rt":"ぶん"}]},{"word":null,"furigana":[{"ruby":"の"}]},{"word":1582120,"furigana":[{"ruby":"店","rt":"みせ"}]},{"word":null,"furigana":[{"ruby":"を"}]},{"word":1315720,"furigana":[{"ruby":"持","rt":"も"},{"ruby":"っている"}]},{"word":null,"furigana":[{"ruby":"。"}]}]}