{"id":193885,"sentence":"もしかこの方面に来るようなことがあったらお寄りください。","meaning":"If you come this way by any chance, drop in to see me.","words":[{"word":2133220,"furigana":[{"ruby":"もしか"}]},{"word":1582920,"furigana":[{"ruby":"この"}]},{"word":1517100,"furigana":[{"ruby":"方","rt":"ほう"},{"ruby":"面","rt":"めん"}]},{"word":null,"furigana":[{"ruby":"に"}]},{"word":1547720,"furigana":[{"ruby":"来","rt":"く"},{"ruby":"る"}]},{"word":2409180,"furigana":[{"ruby":"ような"}]},{"word":1004540,"furigana":[{"ruby":"ことがあったら"}]},{"word":2826528,"furigana":[{"ruby":"お"}]},{"word":1219680,"furigana":[{"ruby":"寄","rt":"よ"},{"ruby":"り"}]},{"word":1184270,"furigana":[{"ruby":"ください"}]},{"word":null,"furigana":[{"ruby":"。"}]}]}