{"id":198093,"sentence":"パスポートに名前が記載されている人は、言葉で述べられていた。","meaning":"The person whose name was on the passport was described with words.","words":[{"word":null,"furigana":[{"ruby":"パスポートに"}]},{"word":1531710,"furigana":[{"ruby":"名","rt":"な"},{"ruby":"前","rt":"まえ"}]},{"word":null,"furigana":[{"ruby":"が"}]},{"word":1223230,"furigana":[{"ruby":"記","rt":"き"},{"ruby":"載","rt":"さい"}]},{"word":2269820,"furigana":[{"ruby":"されている"}]},{"word":1580640,"furigana":[{"ruby":"人","rt":"ひと"}]},{"word":null,"furigana":[{"ruby":"は、"}]},{"word":1264540,"furigana":[{"ruby":"言葉"}]},{"word":null,"furigana":[{"ruby":"で"}]},{"word":1340820,"furigana":[{"ruby":"述","rt":"の"},{"ruby":"べられていた"}]},{"word":null,"furigana":[{"ruby":"。"}]}]}