{"id":201965,"sentence":"テレビを見たりラジオを聞いたりするとき、耳にする音楽はしばしばアフリカ起源のものです。","meaning":"When you watch television or listen to the radio, the music which you hear is often African in origin.","words":[{"word":null,"furigana":[{"ruby":"テレビを"}]},{"word":1259290,"furigana":[{"ruby":"見","rt":"み"},{"ruby":"たり"}]},{"word":null,"furigana":[{"ruby":"ラジオを"}]},{"word":1591110,"furigana":[{"ruby":"聞","rt":"き"},{"ruby":"いたり"}]},{"word":1157170,"furigana":[{"ruby":"する"}]},{"word":1315840,"furigana":[{"ruby":"とき"}]},{"word":null,"furigana":[{"ruby":"、"}]},{"word":2059550,"furigana":[{"ruby":"耳","rt":"みみ"},{"ruby":"にする"}]},{"word":1183720,"furigana":[{"ruby":"音","rt":"おん"},{"ruby":"楽","rt":"がく"}]},{"word":null,"furigana":[{"ruby":"は"}]},{"word":1005580,"furigana":[{"ruby":"しばしば"}]},{"word":1929050,"furigana":[{"ruby":"アフリカ"}]},{"word":1591140,"furigana":[{"ruby":"起","rt":"き"},{"ruby":"源","rt":"げん"}]},{"word":null,"furigana":[{"ruby":"の"}]},{"word":1502390,"furigana":[{"ruby":"もの"}]},{"word":null,"furigana":[{"ruby":"です。"}]}]}