{"id":206026,"sentence":"その話は本当に様には聞こえなかった。","meaning":"The story didn't sound true.","words":[{"word":1006830,"furigana":[{"ruby":"その"}]},{"word":1600900,"furigana":[{"ruby":"話","rt":"はなし"}]},{"word":null,"furigana":[{"ruby":"は"}]},{"word":1611580,"furigana":[{"ruby":"本","rt":"ほん"},{"ruby":"当","rt":"とう"},{"ruby":"に"}]},{"word":1605840,"furigana":[{"ruby":"様","rt":"よう"}]},{"word":null,"furigana":[{"ruby":"には"}]},{"word":1591150,"furigana":[{"ruby":"聞","rt":"き"},{"ruby":"こえなかった"}]},{"word":null,"furigana":[{"ruby":"。"}]}]}