{"id":206329,"sentence":"その野原は野生の花でいっぱいだ。","meaning":"The fields abound in wild flowers.","words":[{"word":1006830,"furigana":[{"ruby":"その"}]},{"word":1537360,"furigana":[{"ruby":"野","rt":"の"},{"ruby":"原","rt":"はら"}]},{"word":null,"furigana":[{"ruby":"は"}]},{"word":1537470,"furigana":[{"ruby":"野","rt":"や"},{"ruby":"生","rt":"せい"},{"ruby":"の"}]},{"word":1194500,"furigana":[{"ruby":"花","rt":"はな"}]},{"word":null,"furigana":[{"ruby":"で"}]},{"word":1165670,"furigana":[{"ruby":"いっぱい"}]},{"word":null,"furigana":[{"ruby":"だ。"}]}]}