{"id":211252,"sentence":"その計画は現在では全く変更の余地がない。","meaning":"The program does not allow for changes at this point in time.","words":[{"word":1006830,"furigana":[{"ruby":"その"}]},{"word":1252090,"furigana":[{"ruby":"計","rt":"けい"},{"ruby":"画","rt":"かく"}]},{"word":null,"furigana":[{"ruby":"は"}]},{"word":1263650,"furigana":[{"ruby":"現","rt":"げん"},{"ruby":"在","rt":"ざい"}]},{"word":null,"furigana":[{"ruby":"では"}]},{"word":1394800,"furigana":[{"ruby":"全","rt":"まった"},{"ruby":"く"}]},{"word":1511040,"furigana":[{"ruby":"変","rt":"へん"},{"ruby":"更","rt":"こう"}]},{"word":null,"furigana":[{"ruby":"の"}]},{"word":1544380,"furigana":[{"ruby":"余","rt":"よ"},{"ruby":"地","rt":"ち"}]},{"word":null,"furigana":[{"ruby":"が"}]},{"word":1529520,"furigana":[{"ruby":"ない"}]},{"word":null,"furigana":[{"ruby":"。"}]}]}