{"id":212732,"sentence":"そのバスは十分遅れで到着した。","meaning":"The bus arrived ten minutes behind time.","words":[{"word":1006830,"furigana":[{"ruby":"その"}]},{"word":null,"furigana":[{"ruby":"バスは"}]},{"word":1335070,"furigana":[{"ruby":"十","rt":"じっ"},{"ruby":"分","rt":"ぷん"}]},{"word":1422020,"furigana":[{"ruby":"遅","rt":"おく"},{"ruby":"れ"}]},{"word":null,"furigana":[{"ruby":"で"}]},{"word":1449870,"furigana":[{"ruby":"到","rt":"とう"},{"ruby":"着","rt":"ちゃく"}]},{"word":1157170,"furigana":[{"ruby":"した"}]},{"word":null,"furigana":[{"ruby":"。"}]}]}