{"id":219930,"sentence":"この物質はそれ自体では有毒ではない。","meaning":"This substance is not poisonous in itself.","words":[{"word":1582920,"furigana":[{"ruby":"この"}]},{"word":1502560,"furigana":[{"ruby":"物","rt":"ぶっ"},{"ruby":"質","rt":"しつ"}]},{"word":null,"furigana":[{"ruby":"は"}]},{"word":2454170,"furigana":[{"ruby":"それ"},{"ruby":"自","rt":"じ"},{"ruby":"体","rt":"たい"}]},{"word":null,"furigana":[{"ruby":"では"}]},{"word":1541550,"furigana":[{"ruby":"有","rt":"ゆう"},{"ruby":"毒","rt":"どく"}]},{"word":2823770,"furigana":[{"ruby":"ではない"}]},{"word":null,"furigana":[{"ruby":"。"}]}]}