{"id":223138,"sentence":"この前の講和会議で完全に失敗してから、彼は斬新な権謀術策で十分に武装すべきことを学んだ。","meaning":"His utter failure at the last peace conference has taught him to arm himself to the teeth with new tricks and tactics.","words":[{"word":1582920,"furigana":[{"ruby":"この"}]},{"word":1392580,"furigana":[{"ruby":"前","rt":"まえ"}]},{"word":null,"furigana":[{"ruby":"の"}]},{"word":1935300,"furigana":[{"ruby":"講","rt":"こう"},{"ruby":"和","rt":"わ"},{"ruby":"会","rt":"かい"},{"ruby":"議","rt":"ぎ"}]},{"word":null,"furigana":[{"ruby":"で"}]},{"word":1211510,"furigana":[{"ruby":"完","rt":"かん"},{"ruby":"全","rt":"ぜん"},{"ruby":"に"}]},{"word":1320140,"furigana":[{"ruby":"失","rt":"しっ"},{"ruby":"敗","rt":"ぱい"}]},{"word":1157170,"furigana":[{"ruby":"して"}]},{"word":null,"furigana":[{"ruby":"から、"}]},{"word":1483070,"furigana":[{"ruby":"彼","rt":"かれ"}]},{"word":null,"furigana":[{"ruby":"は"}]},{"word":1304410,"furigana":[{"ruby":"斬","rt":"ざん"},{"ruby":"新","rt":"しん"},{"ruby":"な"}]},{"word":1258180,"furigana":[{"ruby":"権","rt":"けん"},{"ruby":"謀","rt":"ぼう"}]},{"word":1340810,"furigana":[{"ruby":"術","rt":"じゅっ"},{"ruby":"策","rt":"さく"}]},{"word":null,"furigana":[{"ruby":"で"}]},{"word":1335080,"furigana":[{"ruby":"十","rt":"じゅう"},{"ruby":"分","rt":"ぶん"},{"ruby":"に"}]},{"word":1498740,"furigana":[{"ruby":"武","rt":"ぶ"},{"ruby":"装","rt":"そう"}]},{"word":1006200,"furigana":[{"ruby":"すべき"}]},{"word":1313580,"furigana":[{"ruby":"こと"}]},{"word":null,"furigana":[{"ruby":"を"}]},{"word":1206530,"furigana":[{"ruby":"学","rt":"まな"},{"ruby":"んだ"}]},{"word":null,"furigana":[{"ruby":"。"}]}]}