{"id":225358,"sentence":"ケイトはよくテレビに出演する新人歌手に夢中になっています。","meaning":"Kate is crazy about the new singer who appears on television frequently.","words":[{"word":null,"furigana":[{"ruby":"ケイトは"}]},{"word":1605870,"furigana":[{"ruby":"よく"}]},{"word":null,"furigana":[{"ruby":"テレビに"}]},{"word":1338290,"furigana":[{"ruby":"出","rt":"しゅつ"},{"ruby":"演","rt":"えん"}]},{"word":1157170,"furigana":[{"ruby":"する"}]},{"word":1939030,"furigana":[{"ruby":"新","rt":"しん"},{"ruby":"人","rt":"じん"},{"ruby":"歌","rt":"か"},{"ruby":"手","rt":"しゅ"}]},{"word":null,"furigana":[{"ruby":"に"}]},{"word":1529500,"furigana":[{"ruby":"夢","rt":"む"},{"ruby":"中","rt":"ちゅう"}]},{"word":null,"furigana":[{"ruby":"になっています"}]},{"word":null,"furigana":[{"ruby":"。"}]}]}