{"id":230447,"sentence":"あの本屋でたまたまその本を見つけた。","meaning":"I found the book at that bookstore by chance.","words":[{"word":1000420,"furigana":[{"ruby":"あの"}]},{"word":1522240,"furigana":[{"ruby":"本","rt":"ほん"},{"ruby":"屋","rt":"や"}]},{"word":null,"furigana":[{"ruby":"で"}]},{"word":1597180,"furigana":[{"ruby":"たまたま"}]},{"word":1006830,"furigana":[{"ruby":"その"}]},{"word":1522150,"furigana":[{"ruby":"本","rt":"ほん"}]},{"word":null,"furigana":[{"ruby":"を"}]},{"word":1604570,"furigana":[{"ruby":"見","rt":"み"},{"ruby":"つけた"}]},{"word":null,"furigana":[{"ruby":"。"}]}]}