{"id":2322657,"sentence":"ギリシャは西洋文明の揺籃の地であった。","meaning":"Greece was the cradle of western civilization.","words":[{"word":1043190,"furigana":[{"ruby":"ギリシャ"}]},{"word":null,"furigana":[{"ruby":"は"}]},{"word":1940640,"furigana":[{"ruby":"西","rt":"せい"},{"ruby":"洋","rt":"よう"},{"ruby":"文","rt":"ぶん"},{"ruby":"明","rt":"めい"}]},{"word":null,"furigana":[{"ruby":"の"}]},{"word":1826620,"furigana":[{"ruby":"揺","rt":"よう"},{"ruby":"籃","rt":"らん"},{"ruby":"の"},{"ruby":"地","rt":"ち"}]},{"word":1008340,"furigana":[{"ruby":"であった"}]},{"word":null,"furigana":[{"ruby":"。"}]}]}