{"id":233211,"sentence":"あなたの手紙を間違ってあけてしまってすいませんでした。","meaning":"I'm sorry I opened your mail by mistake.","words":[{"word":1223615,"furigana":[{"ruby":"あなた"}]},{"word":null,"furigana":[{"ruby":"の"}]},{"word":1327720,"furigana":[{"ruby":"手","rt":"て"},{"ruby":"紙","rt":"がみ"}]},{"word":null,"furigana":[{"ruby":"を"}]},{"word":1611610,"furigana":[{"ruby":"間","rt":"ま"},{"ruby":"違","rt":"ちが"},{"ruby":"って"}]},{"word":1202450,"furigana":[{"ruby":"あけて"}]},{"word":1305380,"furigana":[{"ruby":"しまって"}]},{"word":1985560,"furigana":[{"ruby":"すいませんでした"}]},{"word":null,"furigana":[{"ruby":"。"}]}]}