{"id":236371,"sentence":"「割り当て」という概念を考察することから始めよう。","meaning":"We will begin by considering the concept of \"quota\".","words":[{"word":null,"furigana":[{"ruby":"「"}]},{"word":1606820,"furigana":[{"ruby":"割り当て"}]},{"word":null,"furigana":[{"ruby":"」"}]},{"word":1922760,"furigana":[{"ruby":"という"}]},{"word":1204480,"furigana":[{"ruby":"概","rt":"がい"},{"ruby":"念","rt":"ねん"}]},{"word":null,"furigana":[{"ruby":"を"}]},{"word":1281150,"furigana":[{"ruby":"考","rt":"こう"},{"ruby":"察","rt":"さつ"}]},{"word":1157170,"furigana":[{"ruby":"する"}]},{"word":1313580,"furigana":[{"ruby":"こと"}]},{"word":null,"furigana":[{"ruby":"から"}]},{"word":1307550,"furigana":[{"ruby":"始","rt":"はじ"},{"ruby":"めよう"}]},{"word":null,"furigana":[{"ruby":"。"}]}]}