{"id":76908,"sentence":"あっさり断られると思いきや、彼女は承諾してくれました。","meaning":"I had expected an outright refusal, but to my surprise she agreed.","words":[{"word":null,"furigana":[{"ruby":"あっさり"}]},{"word":1419570,"furigana":[{"ruby":"断","rt":"ことわ"},{"ruby":"られる"}]},{"word":null,"furigana":[{"ruby":"と"}]},{"word":2066550,"furigana":[{"ruby":"思","rt":"おも"},{"ruby":"いきや"}]},{"word":null,"furigana":[{"ruby":"、"}]},{"word":1483150,"furigana":[{"ruby":"彼","rt":"かの"},{"ruby":"女","rt":"じょ"}]},{"word":null,"furigana":[{"ruby":"は"}]},{"word":1349470,"furigana":[{"ruby":"承","rt":"しょう"},{"ruby":"諾","rt":"だく"}]},{"word":1157170,"furigana":[{"ruby":"して"}]},{"word":1269130,"furigana":[{"ruby":"くれました"}]},{"word":null,"furigana":[{"ruby":"。"}]}]}