{"id":76917,"sentence":"あおいは、苦学生だから、そんな高級なもの、持てないです。","meaning":"I'm putting myself through school, so I can't have things that are that expensive.","words":[{"word":null,"furigana":[{"ruby":"あおいは、"}]},{"word":1244420,"furigana":[{"ruby":"苦","rt":"く"},{"ruby":"学","rt":"がく"},{"ruby":"生","rt":"せい"}]},{"word":null,"furigana":[{"ruby":"だから、そんな"}]},{"word":1283400,"furigana":[{"ruby":"高","rt":"こう"},{"ruby":"級","rt":"きゅう"},{"ruby":"な"}]},{"word":1502390,"furigana":[{"ruby":"もの"}]},{"word":null,"furigana":[{"ruby":"、"}]},{"word":1315720,"furigana":[{"ruby":"持","rt":"も"},{"ruby":"てない"}]},{"word":null,"furigana":[{"ruby":"です。"}]}]}