{"id":78931,"sentence":"与党は前の選挙で過半数を占めた。","meaning":"The government got their majority at the last election.","words":[{"word":1544870,"furigana":[{"ruby":"与","rt":"よ"},{"ruby":"党","rt":"とう"}]},{"word":null,"furigana":[{"ruby":"は"}]},{"word":1392580,"furigana":[{"ruby":"前","rt":"まえ"}]},{"word":null,"furigana":[{"ruby":"の"}]},{"word":1392190,"furigana":[{"ruby":"選","rt":"せん"},{"ruby":"挙","rt":"きょ"}]},{"word":null,"furigana":[{"ruby":"で"}]},{"word":1196380,"furigana":[{"ruby":"過","rt":"か"},{"ruby":"半","rt":"はん"},{"ruby":"数","rt":"すう"}]},{"word":null,"furigana":[{"ruby":"を"}]},{"word":1389460,"furigana":[{"ruby":"占","rt":"し"},{"ruby":"めた"}]},{"word":null,"furigana":[{"ruby":"。"}]}]}