{"id":79172,"sentence":"郵便局はその通りを下ったところです。","meaning":"The post office is down the street.","words":[{"word":1542430,"furigana":[{"ruby":"郵","rt":"ゆう"},{"ruby":"便","rt":"びん"},{"ruby":"局","rt":"きょく"}]},{"word":null,"furigana":[{"ruby":"は"}]},{"word":2057830,"furigana":[{"ruby":"その"},{"ruby":"通","rt":"とお"},{"ruby":"り"}]},{"word":null,"furigana":[{"ruby":"を"}]},{"word":1184450,"furigana":[{"ruby":"下","rt":"くだ"},{"ruby":"った"}]},{"word":1343100,"furigana":[{"ruby":"ところ"}]},{"word":null,"furigana":[{"ruby":"です。"}]}]}