{"id":81372,"sentence":"妹は朝からずっと編み物をしている。","meaning":"My sister has been knitting since this morning.","words":[{"word":1524590,"furigana":[{"ruby":"妹","rt":"いもうと"}]},{"word":null,"furigana":[{"ruby":"は"}]},{"word":1428280,"furigana":[{"ruby":"朝","rt":"あさ"}]},{"word":null,"furigana":[{"ruby":"からずっと"}]},{"word":1586670,"furigana":[{"ruby":"編","rt":"あ"},{"ruby":"み"},{"ruby":"物","rt":"もの"}]},{"word":null,"furigana":[{"ruby":"を"}]},{"word":1157170,"furigana":[{"ruby":"している"}]},{"word":null,"furigana":[{"ruby":"。"}]}]}