{"id":82811,"sentence":"母親の怒りの厳しさにびっくりした。","meaning":"We were shocked by the intensity of our mother's anger.","words":[{"word":1515120,"furigana":[{"ruby":"母","rt":"はは"},{"ruby":"親","rt":"おや"}]},{"word":null,"furigana":[{"ruby":"の"}]},{"word":1445670,"furigana":[{"ruby":"怒","rt":"いか"},{"ruby":"り"}]},{"word":null,"furigana":[{"ruby":"の"}]},{"word":1262530,"furigana":[{"ruby":"厳","rt":"きび"},{"ruby":"し"}]},{"word":null,"furigana":[{"ruby":"さに"}]},{"word":1226360,"furigana":[{"ruby":"びっくり"}]},{"word":1157170,"furigana":[{"ruby":"した"}]},{"word":null,"furigana":[{"ruby":"。"}]}]}