{"id":83661,"sentence":"文体が作家に持つ関係は、色彩が画家に対するのと同じである。","meaning":"Style is to the writer what color is to the painter.","words":[{"word":1505510,"furigana":[{"ruby":"文","rt":"ぶん"},{"ruby":"体","rt":"たい"}]},{"word":null,"furigana":[{"ruby":"が"}]},{"word":1297510,"furigana":[{"ruby":"作","rt":"さっ"},{"ruby":"家","rt":"か"}]},{"word":null,"furigana":[{"ruby":"に"}]},{"word":1315720,"furigana":[{"ruby":"持","rt":"も"},{"ruby":"つ"}]},{"word":1215810,"furigana":[{"ruby":"関","rt":"かん"},{"ruby":"係","rt":"けい"}]},{"word":null,"furigana":[{"ruby":"は、"}]},{"word":1357720,"furigana":[{"ruby":"色","rt":"しき"},{"ruby":"彩","rt":"さい"}]},{"word":null,"furigana":[{"ruby":"が"}]},{"word":1197120,"furigana":[{"ruby":"画","rt":"が"},{"ruby":"家","rt":"か"}]},{"word":1009810,"furigana":[{"ruby":"に"},{"ruby":"対","rt":"たい"},{"ruby":"する"}]},{"word":null,"furigana":[{"ruby":"のと"}]},{"word":1451750,"furigana":[{"ruby":"同","rt":"おな"},{"ruby":"じ"}]},{"word":null,"furigana":[{"ruby":"である。"}]}]}