{"id":92442,"sentence":"彼女はその時、妹と遊んでいました。","meaning":"She was playing with her sister at that time.","words":[{"word":1483150,"furigana":[{"ruby":"彼","rt":"かの"},{"ruby":"女","rt":"じょ"}]},{"word":null,"furigana":[{"ruby":"は"}]},{"word":1006830,"furigana":[{"ruby":"その"}]},{"word":1315840,"furigana":[{"ruby":"時","rt":"とき"}]},{"word":null,"furigana":[{"ruby":"、"}]},{"word":1524590,"furigana":[{"ruby":"妹","rt":"いもうと"}]},{"word":null,"furigana":[{"ruby":"と"}]},{"word":1542160,"furigana":[{"ruby":"遊","rt":"あそ"},{"ruby":"んでいました"}]},{"word":null,"furigana":[{"ruby":"。"}]}]}