{"id":92624,"sentence":"彼女はそのアイデアが浮かぶとすぐに実行に移した。","meaning":"No sooner had the idea occurred to her than she put it into action.","words":[{"word":1483150,"furigana":[{"ruby":"彼","rt":"かの"},{"ruby":"女","rt":"じょ"}]},{"word":null,"furigana":[{"ruby":"は"}]},{"word":1006830,"furigana":[{"ruby":"その"}]},{"word":null,"furigana":[{"ruby":"アイデアが"}]},{"word":1497430,"furigana":[{"ruby":"浮","rt":"う"},{"ruby":"かぶ"}]},{"word":null,"furigana":[{"ruby":"と"}]},{"word":1430620,"furigana":[{"ruby":"すぐに"}]},{"word":1252100,"furigana":[{"ruby":"実","rt":"じっ"},{"ruby":"行","rt":"こう"},{"ruby":"に"},{"ruby":"移","rt":"うつ"},{"ruby":"した"}]},{"word":null,"furigana":[{"ruby":"。"}]}]}