{"id":98870,"sentence":"彼は老人なので、面倒を見るのは君の役目だ。","meaning":"Now that he is old, it is your duty to look after him.","words":[{"word":1483070,"furigana":[{"ruby":"彼","rt":"かれ"}]},{"word":null,"furigana":[{"ruby":"は"}]},{"word":1561090,"furigana":[{"ruby":"老","rt":"ろう"},{"ruby":"人","rt":"じん"}]},{"word":null,"furigana":[{"ruby":"なので、"}]},{"word":2134390,"furigana":[{"ruby":"面","rt":"めん"},{"ruby":"倒","rt":"どう"},{"ruby":"を"},{"ruby":"見","rt":"み"},{"ruby":"る"}]},{"word":null,"furigana":[{"ruby":"のは"}]},{"word":1247250,"furigana":[{"ruby":"君","rt":"きみ"},{"ruby":"の"}]},{"word":1538080,"furigana":[{"ruby":"役","rt":"やく"},{"ruby":"目","rt":"め"}]},{"word":null,"furigana":[{"ruby":"だ。"}]}]}