{"id":99007,"sentence":"彼は旅行にはあまり手荷物を持ち歩かない。","meaning":"He doesn't carry much baggage on his trips.","words":[{"word":1483070,"furigana":[{"ruby":"彼","rt":"かれ"}]},{"word":null,"furigana":[{"ruby":"は"}]},{"word":1553170,"furigana":[{"ruby":"旅","rt":"りょ"},{"ruby":"行","rt":"こう"}]},{"word":null,"furigana":[{"ruby":"には"}]},{"word":1584930,"furigana":[{"ruby":"あまり"}]},{"word":1327360,"furigana":[{"ruby":"手","rt":"て"},{"ruby":"荷","rt":"に"},{"ruby":"物","rt":"もつ"}]},{"word":null,"furigana":[{"ruby":"を"}]},{"word":1315680,"furigana":[{"ruby":"持","rt":"も"},{"ruby":"ち"},{"ruby":"歩","rt":"ある"},{"ruby":"かない"}]},{"word":null,"furigana":[{"ruby":"。"}]}]}